Metadata-Version: 1.0
Name: yuldistributions
Version: 0.1
Summary: Gaussian and Binomal distributions
Home-page: UNKNOWN
Author: Yulika Wijayanti
Author-email: yulika.wijayanti@gmail.com
License: UNKNOWN
Platform: UNKNOWN
